hive/email/__init__.py
hive/email/__version__.py
hive/email/message.py
hive/email/optional/__init__.py
hive/email/optional/html2text.py
hive_email-0.0.2.dist-info/METADATA
hive_email-0.0.2.dist-info/WHEEL
hive_email-0.0.2.dist-info/top_level.txt
hive_email-0.0.2.dist-info/RECORD
