Metadata-Version: 2.1
Name: hive-email
Version: 0.0.2
Summary: Email message handling for Hive.
Author-email: Gary Benson <gary@gbenson.net>
Project-URL: Homepage, https://github.com/gbenson/hive/tree/main/libs/email
Project-URL: Source, https://github.com/gbenson/hive
Requires-Python: >=3.10
Provides-Extra: html
Requires-Dist: html2text ; extra == 'html'
